foundation_voice/__init__.py
foundation_voice/lib.py
foundation_voice/models.py
foundation_voice/agent/__init__.py
foundation_voice/agent/agent.py
foundation_voice/agent/cleanup.py
foundation_voice/agent/run.py
foundation_voice/custom_plugins/__init__.py
foundation_voice/custom_plugins/agent_callbacks.py
foundation_voice/custom_plugins/frames/__init__.py
foundation_voice/custom_plugins/frames/frames.py
foundation_voice/custom_plugins/processors/aggregators/__init__.py
foundation_voice/custom_plugins/processors/aggregators/agent_context.py
foundation_voice/custom_plugins/services/guardrailed_cerebras/__init__.py
foundation_voice/custom_plugins/services/guardrailed_cerebras/guardrail_llm.py
foundation_voice/custom_plugins/services/guardrailed_cerebras/llm_based_guardrail.py
foundation_voice/custom_plugins/services/openai_agents/llm.py
foundation_voice/custom_plugins/services/openai_agents/agents_sdk/__init__.py
foundation_voice/custom_plugins/services/openai_agents/agents_sdk/agent.py
foundation_voice/custom_plugins/services/openai_agents/agents_sdk/handler.py
foundation_voice/custom_plugins/services/openai_agents/agents_sdk/utils/__init__.py
foundation_voice/custom_plugins/services/openai_agents/agents_sdk/utils/chunks.py
foundation_voice/custom_plugins/services/openai_agents/agents_sdk/utils/models.py
foundation_voice/custom_plugins/services/openai_agents/agents_sdk/utils/tools.py
foundation_voice/custom_plugins/services/smallest/__init__.py
foundation_voice/custom_plugins/services/smallest/tts.py
foundation_voice/utils/__init__.py
foundation_voice/utils/api_utils.py
foundation_voice/utils/config_loader.py
foundation_voice/utils/daily_helpers.py
foundation_voice/utils/function_adapter.py
foundation_voice/utils/provider_utils.py
foundation_voice/utils/webhook_sender.py
foundation_voice/utils/idle_processor/__init__.py
foundation_voice/utils/idle_processor/user_idle_processor.py
foundation_voice/utils/observers/__init__.py
foundation_voice-0.1.3.dist-info/licenses/LICENSE
foundation_voice-0.1.3.dist-info/METADATA
foundation_voice-0.1.3.dist-info/WHEEL
foundation_voice-0.1.3.dist-info/entry_points.txt
foundation_voice-0.1.3.dist-info/top_level.txt
foundation_voice-0.1.3.dist-info/RECORD
