Metadata-Version: 2.4
Name: foundation_voice
Version: 0.1.3
Summary: Core package for Open Source CAI Pipecat - foundation voice
Author: think41
Project-URL: Homepage, https://github.com/think41/foundation-voice.git
Keywords: ai,pipecat,open-source,foundation-voice
Classifier: Programming Language :: Python :: 3
Classifier: License :: OSI Approved :: MIT License
Classifier: Operating System :: OS Independent
Requires-Python: >=3.8
License-File: LICENSE
Requires-Dist: fastapi>=0.115.6
Requires-Dist: loguru>=0.7.0
Requires-Dist: mcp
Requires-Dist: pipecat-ai>=0.0.71
Requires-Dist: pipecat-ai[silero]>=0.0.71
Requires-Dist: pydantic-ai[logfire]>=0.0.51
Requires-Dist: python-dotenv>=1.0.1
Requires-Dist: ruff>=0.8.6
Requires-Dist: uvicorn>=0.30.6
Requires-Dist: websockets>=13.0.1
Requires-Dist: opentelemetry-exporter-otlp-proto-grpc>=1.25.0
Provides-Extra: openai
Requires-Dist: pipecat-ai[openai]>=0.0.71; extra == "openai"
Provides-Extra: openai-agents
Requires-Dist: openai-agents>=0.0.12; extra == "openai-agents"
Provides-Extra: deepgram
Requires-Dist: pipecat-ai[deepgram]>=0.0.71; extra == "deepgram"
Provides-Extra: cartesia
Requires-Dist: pipecat-ai[cartesia]>=0.0.71; extra == "cartesia"
Provides-Extra: daily
Requires-Dist: pipecat-ai[daily]>=0.0.71; extra == "daily"
Provides-Extra: webrtc
Requires-Dist: pipecat-ai[webrtc]>=0.0.71; extra == "webrtc"
Requires-Dist: pipecat-ai-small-webrtc-prebuilt>=0.5.0; extra == "webrtc"
Provides-Extra: smallestai
Requires-Dist: smallestai>=3.1.0; extra == "smallestai"
Provides-Extra: twilio
Requires-Dist: twilio; extra == "twilio"
Provides-Extra: groq
Requires-Dist: pipecat-ai[groq]>=0.0.71; extra == "groq"
Provides-Extra: elevenlabs
Requires-Dist: pipecat-ai[elevenlabs]>=0.0.71; extra == "elevenlabs"
Provides-Extra: all
Requires-Dist: foundation_voice[openai-agents]; extra == "all"
Requires-Dist: foundation_voice[openai]; extra == "all"
Requires-Dist: foundation_voice[deepgram]; extra == "all"
Requires-Dist: foundation_voice[cartesia]; extra == "all"
Requires-Dist: foundation_voice[daily]; extra == "all"
Requires-Dist: foundation_voice[webrtc]; extra == "all"
Requires-Dist: foundation_voice[smallestai]; extra == "all"
Requires-Dist: foundation_voice[twilio]; extra == "all"
Requires-Dist: foundation_voice[groq]; extra == "all"
Requires-Dist: foundation_voice[elevenlabs]; extra == "all"
Dynamic: license-file
